supercellmap/__init__.py
supercellmap/supercell.py
supercellmap/tests.py
supercellmap-0.1.1.dist-info/LICENSE
supercellmap-0.1.1.dist-info/METADATA
supercellmap-0.1.1.dist-info/WHEEL
supercellmap-0.1.1.dist-info/top_level.txt
supercellmap-0.1.1.dist-info/RECORD
